{
  "top":[
    {
      "steamID":"76561198024011621",
      "name":"Aitoreta",
      "url":"https://www.twitch.tv/aitoreta",
      "photo":"https://avatars.cloudflare.steamstatic.com/0388646b693a6f6fe8f540f30afef517029a76db_full.jpg"
    }
  ],
  "list":[
    {
      "steamID":"76561198080462976",
      "name":"CrashDiet",
      "url":"https://www.twitch.tv/crashdiet_05",
      "photo":"https://avatars.steamstatic.com/c1938f818f85b95a612e4951d8392b1d1ed46311_full.jpg"
    },
    {
      "steamID":"76561198104697018",
      "name":"WolfOnF1r3",
      "url":"https://www.twitch.tv/wolfonf1r3",
      "photo":"https://avatars.cloudflare.steamstatic.com/5e116838041f72965c3f4a4670d46a649e092c6c_full.jpg"
    },
    {
      "steamID":"76561198091646120",
      "name":"GameHauntings",
      "url":"https://www.twitch.tv/gamehauntings",
      "photo":"https://avatars.cloudflare.steamstatic.com/25523c04aa68e343389ad3a12f9dbc6ab70733c3_full.jpg"
    },
    {
      "steamID":"76561199128139064",
      "name":"dm_darkqueen",
      "url":"https://www.twitch.tv/dm_darkqueen",
      "photo":"https://avatars.cloudflare.steamstatic.com/0d03ceeab5d673b969786349eeffa7ea478adf28_full.jpg"
    },
    {
      "steamID":"76561199196926236",
      "name":"NocturnalNemz",
      "url":"https://twitch.tv/nocturnalnemz",
      "photo":"https://avatars.cloudflare.steamstatic.com/ca24f8a46894e65d026b5e0a40b7d71dd771655c_full.jpg"
    },
    {
      "steamID":"76561198117412530",
      "name":"Ninggeez",
      "url":"http://www.twitch.tv/ninggeez",
      "photo":"https://avatars.cloudflare.steamstatic.com/844fed6c609968b1a4275e1622258e0212ee484e_full.jpg"
    },
    {
      "steamID":"76561199643172869",
      "name":"Slassti",
      "url":"https://www.twitch.tv/slassti",
      "photo":"https://avatars.steamstatic.com/30ea93f818a0afae26e72372e749100e983f4c9b_full.jpg"
    },
    {
      "steamID":"76561198973991262",
      "name":"Meatba",
      "url":"https://www.twitch.tv/meatba",
      "photo":"https://static-cdn.jtvnw.net/jtv_user_pictures/ec166add-9bef-4679-b62d-e5d3724986b9-profile_image-70x70.png"
    },
    {
      "steamID":"76561199242350389",
      "name":"kresti4k",
      "url":"https://www.tiktok.com/@kresti4k",
      "photo":"https://p58-sign-sg.tiktokcdn.com/aweme/1080x1080/tos-alisg-avt-0068/832b9c7250cc935e76c73d50b2939206.jpeg"
    },
    {
      "steamID":"76561198966274739",
      "name":"Bulbolt",
      "url":"https://www.twitch.tv/bulbolt",
      "photo":"https://avatars.fastly.steamstatic.com/adb24eb5c6258f907f92ac4c4b50af6f08c6d5ff_full.jpg"
    },
    {
      "steamID":"76561198306682760",
      "name":"xNeysha",
      "url":"https://www.twitch.tv/xneysha",
      "photo":"https://avatars.fastly.steamstatic.com/257c4b0378a683c6843af2d2bb179630171a5874_full.jpg"
    },
    {
      "steamID":"76561198096634988",
      "name":"LittleBlackHood",
      "url":"https://www.twitch.tv/littleblackhood",
      "photo":"https://avatars.steamstatic.com/bb4da6bed3fc35ec5fcf093a6786616c3d210897_full.jpg"
    },
    {
      "steamID":"76561198182840647",
      "name":"AdriCano13",
      "url":"https://www.twitch.tv/adricano13",
      "photo":"https://avatars.steamstatic.com/51cfee658ca02a33ab56006739b9d8f828d4d579_full.jpg"
    },
    {
      "steamID":"76561198050197774",
      "name":"Sentishock",
      "url":"https://www.twitch.tv/sentishock",
      "photo":"https://avatars.steamstatic.com/511ece306d8b77b0fcfadb1e0dbdd892331690a8_full.jpg"
    },
    {
      "steamID":"76561199108416371",
      "name":"DarkSora",
      "url":"https://www.twitch.tv/darksora_protocute",
      "photo":"https://avatars.fastly.steamstatic.com/85322b53630a06b59417209027e97cd659be4038_full.jpg"
    },
    {
      "steamID":"76561198198407398",
      "name":"JustSomeDude44",
      "url":"https://www.twitch.tv/justsomedude44",
      "photo":"https://avatars.fastly.steamstatic.com/26321b7f91031c001662257728d06d53a9daccd2_full.jpg"
    },
    {
      "steamID":"76561199535774808",
      "name":"DotWonk",
      "url":"https://www.twitch.tv/dotwonk",
      "photo":"https://avatars.fastly.steamstatic.com/d089668a87179b08bb1d30359fc70c4f0f525d10_full.jpg"
    },
    {
      "steamID":"76561198187687375",
      "name":"BabaYaga",
      "url":"https://www.twitch.tv/bryanxbabayaga",
      "photo":"https://static-cdn.jtvnw.net/jtv_user_pictures/92d960fe-5766-445b-876b-82055f9779ae-profile_image-70x70.png"
    },
    {
      "steamID":"76561199097896043",
      "name":"UrFavSavage",
      "url":"https://kick.com/urfavsavage",
      "photo":"https://pbs.twimg.com/profile_images/1641101768149934085/y8Z8cRhn_400x400.jpg"
    },
    {
      "steamID":"76561199668006154",
      "name":"JessVorhees",
      "url":"http://twitch.tv/jessvorhees",
      "photo":"https://static-cdn.jtvnw.net/jtv_user_pictures/c34caed5-f557-4789-9eb3-0a191bdf3435-profile_image-70x70.png"
    },
    {
      "steamID":"76561197997048047",
      "name":"Davicyyo (dev)",
      "url":"https://www.twitch.tv/davicyyotv",
      "photo":"https://static-cdn.jtvnw.net/jtv_user_pictures/faa250ea-e7a0-4fb9-94d3-7ce76f8cd867-profile_image-70x70.png"
    },
    {
      "steamID":"76561198054997391",
      "name":"Herohayo",
      "url":"https://www.twitch.tv/herohayo",
      "photo":"https://static-cdn.jtvnw.net/jtv_user_pictures/568e7fbf-9ca7-4c40-82f7-89b912c44076-profile_image-70x70.png"
    },
    {
      "steamID":"76561198120817292",
      "name":"FaNtMxAces",
      "url":"https://www.twitch.tv/fantmxaces",
      "photo":"https://static-cdn.jtvnw.net/jtv_user_pictures/fb89df07-04c0-4a8f-99aa-22024d2997cb-profile_image-70x70.png"
    },
    {
      "steamID":"76561198099729711",
      "name":"gelius_gelius",
      "url":"https://www.twitch.tv/gelius_gelius",
      "photo":"https://static-cdn.jtvnw.net/jtv_user_pictures/521b769f-e0bc-4a26-bb89-21c907001148-profile_image-70x70.png"
    }
  ]
}
