[
    {
        "singleplayer": [
            {
                "map": "cabinMap",
                "value": 2
            }
        ],
        "multiplayer": [
            {
                "map": "toyFactoryMap",
                "value": 1
            }
        ],
        "extras": {
            "random": "daycareMap",
            "time_trial": {
                "map": "circusMap",
                "value": 3
            }
        },
        "career": {
            "map": "career",
            "value": 1
        }
    },
    {
        "singleplayer": [
            {
                "map": "houseMap",
                "value": 2
            },
            {
                "map": "toyFactoryMap",
                "value": 2
            },
            {
                "map": "cabinMap",
                "value": 3
            },
            {
                "map": "circusMap",
                "value": 1
            }
        ],
        "multiplayer": [],
        "extras": {
            "random": "houseMap",
            "time_trial": {
                "map": "cabinMap",
                "value": 1
            }
        },
        "career": {
            "map": "career",
            "value": 0
        }
    },
    {
        "singleplayer": [
            {
                "map": "cabinMap",
                "value": 1
            }
        ],
        "multiplayer": [
            {
                "map": "houseMap",
                "value": 0
            }
        ],
        "extras": {
            "random": "houseMap",
            "time_trial": {
                "map": "cabinMap",
                "value": 1
            }
        },
        "career": {
            "map": "career",
            "value": 0
        }
    },
    {
        "singleplayer": [
            {
                "map": "daycareMap",
                "value": 3
            },
            {
                "map": "cabinMap",
                "value": 0
            }
        ],
        "multiplayer": [],
        "extras": {
            "random": "daycareMap",
            "time_trial": {
                "map": "circusMap",
                "value": 2
            }
        },
        "career": {
            "map": "career",
            "value": 1
        }
    },
    {
        "singleplayer": [
            {
                "map": "houseMap",
                "value": 2
            },
            {
                "map": "circusMap",
                "value": 3
            },
            {
                "map": "cabinMap",
                "value": 1
            },
            {
                "map": "daycareMap",
                "value": 0
            }
        ],
        "multiplayer": [],
        "extras": {
            "time_trial": {
                "map": "cabinMap",
                "value": 3
            },
            "endless": {
                "map": "cabinMap",
                "value": 2
            }
        },
        "career": {
            "map": "career",
            "value": 0
        }
    },
    {
        "singleplayer": [
            {
                "map": "cabinMap",
                "value": 3
            }
        ],
        "multiplayer": [
            {
                "map": "circusMap",
                "value": 1
            }
        ],
        "extras": {
            "random": "circusMap",
            "time_trial": {
                "map": "circusMap",
                "value": 1
            }
        },
        "career": {
            "map": "career",
            "value": 1
        }
    },
    {
        "singleplayer": [
            {
                "map": "cabinMap",
                "value": 0
            }
        ],
        "multiplayer": [],
        "extras": {
            "random": "houseMap",
            "time_trial": {
                "map": "circusMap",
                "value": 1
            }
        },
        "career": {
            "map": "career",
            "value": 0
        }
    }
]